atomic_bomb_engine_py-0.3.7.dist-info/METADATA
atomic_bomb_engine_py-0.3.7.dist-info/WHEEL
atomic_bomb_engine.libs/libssl-97000013.so.3
atomic_bomb_engine.libs/libcrypto-dc65c00a.so.3
atomic_bomb_engine/__init__.py
atomic_bomb_engine/__init__.pyi
atomic_bomb_engine/py.typed
atomic_bomb_engine/atomic_bomb_engine.cpython-311-x86_64-linux-gnu.so
atomic_bomb_engine_py-0.3.7.dist-info/RECORD
