Metadata-Version: 2.1
Name: atomic-bomb-engine-py
Version: 0.3.7
